ckanext_datasetpreview-0.2.38-py2.7-nspkg.pth
ckanext/datasetpreview/__init__.py
ckanext/datasetpreview/controllers.py
ckanext/datasetpreview/helpers.py
ckanext/datasetpreview/plugin.py
ckanext/datasetpreview/templates/dataset-preview/chart.html
ckanext/datasetpreview/templates/package/search.html
ckanext/datasetpreview/templates/snippets/package_item.html
ckanext/datasetpreview/tests/__init__.py
ckanext/datasetpreview/tests/test_plugin.py
ckanext_datasetpreview-0.2.38.dist-info/LICENSE
ckanext_datasetpreview-0.2.38.dist-info/METADATA
ckanext_datasetpreview-0.2.38.dist-info/WHEEL
ckanext_datasetpreview-0.2.38.dist-info/entry_points.txt
ckanext_datasetpreview-0.2.38.dist-info/namespace_packages.txt
ckanext_datasetpreview-0.2.38.dist-info/pbr.json
ckanext_datasetpreview-0.2.38.dist-info/top_level.txt
ckanext_datasetpreview-0.2.38.dist-info/RECORD
