Metadata-Version: 2.1
Name: ckanext-datasetpreview
Version: 0.2.38
Summary: Preview for datasets
Home-page: https://github.com/avdata99/ckanext-datasetpreview
Author: Andres vazquez
Author-email: andres@data99.com.ar
License: MIT
Keywords: CKAN chart preview
Platform: UNKNOWN
Classifier: Development Status :: 4 - Beta
Classifier: License :: OSI Approved :: GNU Affero General Public License v3 or later (AGPLv3+)
Classifier: Programming Language :: Python :: 2.7
